{
	"animations": [
		{
			"offsets": [
				-1,
				0
			],
			"loop": false,
			"fps": 24,
			"anim": "idle",
			"indices": [],
			"name": "bf_idle"
		},
		{
			"offsets": [
				50,
				-10
			],
			"loop": false,
			"fps": 24,
			"anim": "singLEFT",
			"indices": [],
			"name": "bf_left"
		},
		{
			"offsets": [
				6,
				-16
			],
			"loop": false,
			"fps": 24,
			"anim": "singDOWN",
			"indices": [],
			"name": "bf_down"
		},
		{
			"offsets": [
				70,
				13
			],
			"loop": false,
			"fps": 24,
			"anim": "singUP",
			"indices": [],
			"name": "bf_up"
		},
		{
			"offsets": [
				0,
				0
			],
			"loop": false,
			"fps": 24,
			"anim": "singRIGHT",
			"indices": [],
			"name": "bf_right"
		},
		{
			"offsets": [
				334,
				357
			],
			"loop": false,
			"fps": 30,
			"anim": "looking",
			"indices": [],
			"name": "bf_looking"
		}
	],
	"no_antialiasing": false,
	"image": "characters/bf_rushwalk",
	"position": [
		0,
		300
	],
	"healthicon": "bf",
	"flip_x": true,
	"healthbar_colors": [
		49,
		176,
		209
	],
	"camera_position": [
		0,
		0
	],
	"sing_duration": 6.1,
	"scale": 1
}